README.md
setup.py
pyaria2/__init__.py
pyaria2.egg-info/PKG-INFO
pyaria2.egg-info/SOURCES.txt
pyaria2.egg-info/dependency_links.txt
pyaria2.egg-info/top_level.txt